{
    "2020": {
        "Information Extraction/Retrieval": 0.5717679944095039,
        "Syntax": 0.7848837209302325,
        "Linguistic Theories and Psycholinguistics": 0.8122222222222222,
        "Applications": 0.6651690821256039,
        "Machine Translation and Multilinguality": 0.5884009009009009,
        "Multimodality, Speech and Grounding": 0.5802543507362784,
        "Sentiment Analysis": 0.5624131944444445,
        "Phonology, Morphology and Word Segmentation": 0.831899641577061,
        "Dialogue": 0.5614222222222223,
        "Social Science": 0.6803497942386831,
        "Question Answering": 0.5398611111111111,
        "Resources and Evaluation": 0.5661616161616162,
        "Generation": 0.5587378640776699,
        "Summarization": 0.4692167577413479,
        "Semantics": 0.6064516129032258,
        "Machine Learning": 0.5924036281179138,
        "Discourse and Pragmatics": 0.7351111111111112
    },
    "2021": {
        "Information Extraction/Retrieval": 0.47301790281329925,
        "Syntax": 0.6971677559912854,
        "Applications": 0.603709591944886,
        "Machine Translation and Multilinguality": 0.5405405405405406,
        "Multimodality, Speech and Grounding": 0.4708267090620032,
        "Sentiment Analysis": 0.49750201450443193,
        "Dialogue": 0.5048552754435107,
        "Social Science": 0.5941176470588235,
        "Question Answering": 0.4647058823529412,
        "Resources and Evaluation": 0.45746130030959753,
        "Generation": 0.5214626391096979,
        "Summarization": 0.47411764705882353,
        "Semantics": 0.527952576379389,
        "Ethics": 0.3526854219948849,
        "Machine Learning": 0.49875100725221594,
        "Discourse and Pragmatics": 0.7815508021390374,
        "Efficient Methods": 0.41897533206831117
    },
    "2022": {
        "Information Extraction/Retrieval": 0.565753781950965,
        "Syntax": 0.718456572769953,
        "Linguistic Theories and Psycholinguistics": 0.6738156209987196,
        "Applications": 0.5650465291750503,
        "Machine Translation and Multilinguality": 0.572370392568175,
        "Multimodality, Speech and Grounding": 0.49168850311169343,
        "Sentiment Analysis": 0.5776848591549296,
        "Dialogue": 0.5295924483068625,
        "Social Science": 0.645099765258216,
        "Question Answering": 0.4990316901408451,
        "Resources and Evaluation": 0.4936678896910877,
        "Generation": 0.5630559673832468,
        "Summarization": 0.4651566113096489,
        "Semantics": 0.5211267605633803,
        "Ethics": 0.40702548625083834,
        "Machine Learning": 0.4387323943661972,
        "Efficient Methods": 0.6666666666666666
    },
    "2023": {
        "Information Extraction/Retrieval": 0.5839285714285715,
        "Syntax": 0.7388888888888889,
        "Linguistic Theories and Psycholinguistics": 0.6342708333333333,
        "Large Language Models": 0.2914156626506024,
        "Applications": 0.5912394662921349,
        "Industry": 0.7002878289473684,
        "Machine Translation and Multilinguality": 0.5710390127388535,
        "Multimodality, Speech and Grounding": 0.5616652397260274,
        "Sentiment Analysis": 0.7058647260273972,
        "Dialogue": 0.5923315602836879,
        "Social Science": 0.571239406779661,
        "Question Answering": 0.5023097826086956,
        "Resources and Evaluation": 0.532298018292683,
        "Generation": 0.5098714953271029,
        "Summarization": 0.5039772727272728,
        "Semantics": 0.6196527777777778,
        "Ethics": 0.45784313725490194,
        "Machine Learning": 0.5140742481203008,
        "Discourse and Pragmatics": 0.6459635416666667,
        "Efficient Methods": 0.6052884615384615
    }
}